pydenv/__init__.py
pydenv/__main__.py
pydenv/pydenv.py
pydenv-1.0.5.dist-info/LICENSE.txt
pydenv-1.0.5.dist-info/METADATA
pydenv-1.0.5.dist-info/WHEEL
pydenv-1.0.5.dist-info/top_level.txt
pydenv-1.0.5.dist-info/RECORD
